CHANGELOG.rst
CONTRIBUTING.md
LICENSE.txt
README.rst
pelican/plugins/jinja_filters/__init__.py
pelican/plugins/jinja_filters/jinja_filters.py
pelican_jinja_filters-2.1.1.dist-info/LICENSE.txt
pelican_jinja_filters-2.1.1.dist-info/WHEEL
pelican_jinja_filters-2.1.1.dist-info/METADATA
pelican_jinja_filters-2.1.1.dist-info/RECORD
