Metadata-Version: 2.1
Name: pelican-jinja-filters
Version: 2.1.1
Summary: Pelican plugin for applying useful Jinja filters in theme templates
Home-page: https://github.com/pelican-plugins/jinja-filters
License: MIT
Keywords: jinja2,templates,pelican,plugin
Author: William Minchin
Author-email: w_minchin@hotmail.com
Requires-Python: >=3.6.2,<4.0
Classifier: Development Status :: 5 - Production/Stable
Classifier: Environment :: Console
Classifier: Framework :: Pelican
Classifier: Framework :: Pelican :: Plugins
Classifier: Intended Audience :: End Users/Desktop
Classifier: License :: OSI Approved :: MIT License
Classifier: Operating System :: OS Independent
Classifier: Programming Language :: Python
Classifier: Programming Language :: Python :: 3
Classifier: Programming Language :: Python :: 3.6
Classifier: Programming Language :: Python :: 3.7
Classifier: Programming Language :: Python :: 3.8
Classifier: Programming Language :: Python :: 3.9
Classifier: Topic :: Internet :: WWW/HTTP
Classifier: Topic :: Software Development :: Libraries :: Python Modules
Provides-Extra: markdown
Requires-Dist: markdown (>=3.2,<4.0); extra == "markdown"
Requires-Dist: pelican (>=3,<5)
Requires-Dist: titlecase (>=1.1.1,<3)
Project-URL: Bug Tracker, https://github.com/pelican-plugins/jinja-filters/issues
Project-URL: Changelog, https://github.com/pelican-plugins/jinja-filters/blob/master/CHANGELOG.rst
Project-URL: Documentation, https://github.com/pelican-plugins/jinja-filters/blob/master/README.rst
Project-URL: Funding, https://donate.getpelican.com/
Project-URL: Repository, https://github.com/pelican-plugins/jinja-filters
